scikit_event_correlation/__init__.py
scikit_event_correlation/classifiers.py
scikit_event_correlation/cumsum.py
scikit_event_correlation/shewahart.py
scikit_event_correlation-1.0.2.dist-info/LICENSE
scikit_event_correlation-1.0.2.dist-info/METADATA
scikit_event_correlation-1.0.2.dist-info/WHEEL
scikit_event_correlation-1.0.2.dist-info/top_level.txt
scikit_event_correlation-1.0.2.dist-info/RECORD
