Metadata-Version: 2.1
Name: scikit-event-correlation
Version: 1.0.2
Summary: Event Correlation and Changing Detection Algorithm
Home-page: https://github.com/Intellia-SME/scikit-event-correlation
Author: Marilena Athanasiou
Author-email: info@intellia.gr
License: BSD-3-Clause License
Project-URL: Changelog, https://github.com/Intellia-SME/scikit-event-correlation/blob/main/HISTORY.md
Project-URL: Twitter, https://twitter.com/intellia_gr
Project-URL: Bug Tracker, https://github.com/Intellia-SME/scikit-event-correlation/issues
Keywords: Scikit-learn
Platform: UNKNOWN
Classifier: Development Status :: 5 - Production/Stable
Classifier: Intended Audience :: Developers
Classifier: Intended Audience :: Science/Research
Classifier: Programming Language :: Python :: 3 :: Only
Classifier: License :: OSI Approved :: BSD License
Classifier: Operating System :: OS Independent
Classifier: Natural Language :: English
Requires-Python: >=3.6
License-File: LICENSE
Requires-Dist: scikit-learn (>=1.0.2)
Requires-Dist: pandas (>=1.4.0)
